urlreplacer
