Metadata-Version: 1.1
Name: urlreplacer
Version: 0.1.1
Summary: Find and replace URLs in plain text messages
Home-page: https://github.com/tictail/urlreplacer
Author: Tictail
Author-email: tech+pip-urlreplacer@tictail.com
License: MIT
Keywords: url,email,replace
Platform: UNKNOWN
Classifier: License :: OSI Approved :: MIT License
Classifier: Operating System :: OS Independent
Classifier: Programming Language :: Python :: 2.7
